{
  "lastUpdated": "2026-03-26T14:00:00.212103+00:00",
  "indices": {
    "btc": {
      "value": 10,
      "classification": "Extreme Fear",
      "source": "https://nitter.net/BitcoinFear/rss",
      "sourcePost": "https://nitter.net/BitcoinFear/status/2037152613930602501#m",
      "sourcePublishedAt": "Thu, 26 Mar 2026 13:00:06 GMT"
    },
    "eth": {
      "value": 32,
      "classification": "Fear",
      "source": "https://nitter.net/EthereumFear/rss",
      "sourcePost": "https://nitter.net/EthereumFear/status/2037122419580694829#m",
      "sourcePublishedAt": "Thu, 26 Mar 2026 11:00:07 GMT"
    }
  }
}
