{
  "prices": [
    {
      "symbol": "IREN",
      "name": "Iris Energy",
      "price": 42.585,
      "change": -0.87,
      "type": "stock"
    },
    {
      "symbol": "CIFR",
      "name": "Cipher Mining",
      "price": 14.93,
      "change": -1.06,
      "type": "stock"
    },
    {
      "symbol": "STRC",
      "name": "Strategy STRC",
      "price": 99.875,
      "change": 0,
      "type": "stock"
    },
    {
      "symbol": "IBTC.XA",
      "name": "Monochrome Bitcoin ETF",
      "price": 10.4,
      "change": -0.38,
      "type": "stock"
    },
    {
      "symbol": "VBTC.AX",
      "name": "Vaneck Bitcoin ETF",
      "price": 21.1,
      "change": -0.75,
      "type": "stock"
    },
    {
      "symbol": "SPX",
      "name": "S&P 500",
      "price": 6697.9902,
      "change": -0.27,
      "type": "index"
    },
    {
      "symbol": "NDX",
      "name": "NASDAQ 100",
      "price": 24743.0996,
      "change": -0.15,
      "type": "index"
    },
    {
      "symbol": "GOLD",
      "name": "Gold/oz",
      "price": 4883.2998,
      "change": -2.35,
      "type": "commodity"
    },
    {
      "symbol": "SILVER",
      "name": "Silver/oz",
      "price": 77.57,
      "change": -2.46,
      "type": "commodity"
    },
    {
      "symbol": "USDAUD",
      "name": "USD/AUD",
      "price": 1.4139,
      "change": -0.06,
      "type": "forex"
    }
  ],
  "lastUpdated": "2026-03-19T01:10:07.405445"
}