{
  "prices": [
    {
      "symbol": "IREN",
      "name": "Iris Energy",
      "price": 44.64,
      "change": 4.15,
      "type": "stock"
    },
    {
      "symbol": "CIFR",
      "name": "Cipher Mining",
      "price": 17.84,
      "change": 5.44,
      "type": "stock"
    },
    {
      "symbol": "IBTC.XA",
      "name": "Monochrome Bitcoin ETF",
      "price": 10.51,
      "change": -1.78,
      "type": "stock"
    },
    {
      "symbol": "VBTC.AX",
      "name": "Vaneck Bitcoin ETF",
      "price": 21.44,
      "change": -1.74,
      "type": "stock"
    },
    {
      "symbol": "TAO22974-USD",
      "name": "Bittensor USD",
      "price": 250.03,
      "change": -1.53,
      "type": "stock"
    },
    {
      "symbol": "CC37263-USD",
      "name": "Canton Network USD",
      "price": 0.1502,
      "change": -0.7,
      "type": "stock"
    },
    {
      "symbol": "QQQI",
      "name": "Neos Nasdaq 100 Income ETF",
      "price": 54.1599,
      "change": 0.56,
      "type": "stock"
    },
    {
      "symbol": "GPIX",
      "name": "Goldman Sachs Income ETF",
      "price": 54.07,
      "change": 0.71,
      "type": "stock"
    },
    {
      "symbol": "VEA",
      "name": "Vanguard FTSE Developed markets ETF",
      "price": 68.745,
      "change": 2.48,
      "type": "stock"
    },
    {
      "symbol": "VEU",
      "name": "Vanguard FTSE All-world ex-US ETF",
      "price": 80.82,
      "change": 2.14,
      "type": "stock"
    },
    {
      "symbol": "VWO",
      "name": "Vanguard Emerging markets ETF",
      "price": 58.77,
      "change": 1.19,
      "type": "stock"
    },
    {
      "symbol": "STRC",
      "name": "Strategy STRC",
      "price": 99.75,
      "change": 0.28,
      "type": "stock"
    },
    {
      "symbol": "XLE",
      "name": "Energy ETF",
      "price": 59.36,
      "change": 0.56,
      "type": "stock"
    },
    {
      "symbol": "SMH",
      "name": "Semi ETF",
      "price": 506.07,
      "change": 1.3,
      "type": "stock"
    },
    {
      "symbol": "GLW",
      "name": "Corning Inc",
      "price": 162.62,
      "change": 7.06,
      "type": "stock"
    },
    {
      "symbol": "SPX",
      "name": "S&P 500",
      "price": 7201.5,
      "change": 0.92,
      "type": "index"
    },
    {
      "symbol": "NDX",
      "name": "NASDAQ 100",
      "price": 27430.6133,
      "change": 0.9,
      "type": "index"
    },
    {
      "symbol": "GOLD",
      "name": "Gold/oz",
      "price": 4635.7002,
      "change": 1.99,
      "type": "commodity"
    },
    {
      "symbol": "SILVER",
      "name": "Silver/oz",
      "price": 74.22,
      "change": 3.7,
      "type": "commodity"
    },
    {
      "symbol": "BZ",
      "name": "Brent Crude",
      "price": 109.21,
      "change": -7.47,
      "type": "commodity"
    },
    {
      "symbol": "CL",
      "name": "WTI Crude",
      "price": 103.96,
      "change": -2.73,
      "type": "commodity"
    },
    {
      "symbol": "USDAUD",
      "name": "USD/AUD",
      "price": 1.3899,
      "change": -0.11,
      "type": "forex"
    }
  ],
  "lastUpdated": "2026-05-01T04:20:14.384196"
}