{
  "prices": [
    {
      "symbol": "IREN",
      "name": "Iris Energy",
      "price": 37.1799,
      "change": 4.03,
      "type": "stock"
    },
    {
      "symbol": "CIFR",
      "name": "Cipher Mining",
      "price": 15.195,
      "change": 8.46,
      "type": "stock"
    },
    {
      "symbol": "IBTC.XA",
      "name": "Monochrome Bitcoin ETF",
      "price": 10.11,
      "change": 2.54,
      "type": "stock"
    },
    {
      "symbol": "VBTC.AX",
      "name": "Vaneck Bitcoin ETF",
      "price": 20.46,
      "change": 2.3,
      "type": "stock"
    },
    {
      "symbol": "QQQI",
      "name": "Neos Nasdaq 100 Income ETF",
      "price": 51.6482,
      "change": 2.25,
      "type": "stock"
    },
    {
      "symbol": "GPIX",
      "name": "Goldman Sachs Income ETF",
      "price": 51.395,
      "change": 2.14,
      "type": "stock"
    },
    {
      "symbol": "VEA",
      "name": "Vanguard FTSE Developed markets ETF",
      "price": 67.705,
      "change": 4.02,
      "type": "stock"
    },
    {
      "symbol": "VEU",
      "name": "Vanguard FTSE All-world ex-US ETF",
      "price": 79.125,
      "change": 4.1,
      "type": "stock"
    },
    {
      "symbol": "VWO",
      "name": "Vanguard Emerging markets ETF",
      "price": 56.515,
      "change": 4.48,
      "type": "stock"
    },
    {
      "symbol": "STRC",
      "name": "Strategy STRC",
      "price": 100.0099,
      "change": 0.01,
      "type": "stock"
    },
    {
      "symbol": "XLE",
      "name": "Energy ETF",
      "price": 57.29,
      "change": -4.77,
      "type": "stock"
    },
    {
      "symbol": "SMH",
      "name": "Semi ETF",
      "price": 421.43,
      "change": 5.38,
      "type": "stock"
    },
    {
      "symbol": "GLW",
      "name": "Corning Inc",
      "price": 160.795,
      "change": 8.26,
      "type": "stock"
    },
    {
      "symbol": "SPX",
      "name": "S&P 500",
      "price": 6778.1401,
      "change": 2.44,
      "type": "index"
    },
    {
      "symbol": "NDX",
      "name": "NASDAQ 100",
      "price": 24936.2344,
      "change": 3.03,
      "type": "index"
    },
    {
      "symbol": "GOLD",
      "name": "Gold/oz",
      "price": 4776.8999,
      "change": 2.57,
      "type": "commodity"
    },
    {
      "symbol": "SILVER",
      "name": "Silver/oz",
      "price": 75.43,
      "change": 5.02,
      "type": "commodity"
    },
    {
      "symbol": "BZ",
      "name": "Brent Crude",
      "price": 94.78,
      "change": -13.26,
      "type": "commodity"
    },
    {
      "symbol": "CL",
      "name": "WTI Crude",
      "price": 95.41,
      "change": -15.53,
      "type": "commodity"
    },
    {
      "symbol": "USDAUD",
      "name": "USD/AUD",
      "price": 1.4174,
      "change": -2.0,
      "type": "forex"
    }
  ],
  "lastUpdated": "2026-04-09T02:35:14.743273"
}