{
  "prices": [
    {
      "symbol": "IREN",
      "name": "Iris Energy",
      "price": 42.52,
      "change": 2.78,
      "type": "stock"
    },
    {
      "symbol": "CIFR",
      "name": "Cipher Mining",
      "price": 14.5601,
      "change": 6.2,
      "type": "stock"
    },
    {
      "symbol": "STRC",
      "name": "Strategy STRC",
      "price": 99.7195,
      "change": -0.29,
      "type": "stock"
    },
    {
      "symbol": "SPX",
      "name": "S&P 500",
      "price": 6650.23,
      "change": -0.34,
      "type": "index"
    },
    {
      "symbol": "NDX",
      "name": "NASDAQ 100",
      "price": 24420.8027,
      "change": -0.46,
      "type": "index"
    },
    {
      "symbol": "GOLD",
      "name": "Gold/oz",
      "price": 5031.7002,
      "change": -1.64,
      "type": "commodity"
    },
    {
      "symbol": "SILVER",
      "name": "Silver/oz",
      "price": 79.63,
      "change": -5.95,
      "type": "commodity"
    },
    {
      "symbol": "USDAUD",
      "name": "USD/AUD",
      "price": 1.4273,
      "change": 1.72,
      "type": "forex"
    }
  ],
  "lastUpdated": "2026-03-14T03:15:06.453768"
}