{
  "prices": [
    {
      "symbol": "IREN",
      "name": "Iris Energy",
      "price": 31.46,
      "change": -7.71,
      "type": "stock"
    },
    {
      "symbol": "CIFR",
      "name": "Cipher Mining",
      "price": 11.9101,
      "change": -5.77,
      "type": "stock"
    },
    {
      "symbol": "IBTC.XA",
      "name": "Monochrome Bitcoin ETF",
      "price": 9.57,
      "change": -2.59,
      "type": "stock"
    },
    {
      "symbol": "VBTC.AX",
      "name": "Vaneck Bitcoin ETF",
      "price": 19.46,
      "change": -2.65,
      "type": "stock"
    },
    {
      "symbol": "QQQI",
      "name": "Neos Nasdaq 100 Income ETF",
      "price": 49.33,
      "change": -1.71,
      "type": "stock"
    },
    {
      "symbol": "GPIX",
      "name": "Goldman Sachs Income ETF",
      "price": 49.3261,
      "change": -1.35,
      "type": "stock"
    },
    {
      "symbol": "VEA",
      "name": "Vanguard FTSE Developed markets ETF",
      "price": 63.465,
      "change": -2.57,
      "type": "stock"
    },
    {
      "symbol": "VEU",
      "name": "Vanguard FTSE All-world ex-US ETF",
      "price": 74.245,
      "change": -2.42,
      "type": "stock"
    },
    {
      "symbol": "VWO",
      "name": "Vanguard Emerging markets ETF",
      "price": 53.055,
      "change": -2.13,
      "type": "stock"
    },
    {
      "symbol": "STRC",
      "name": "Strategy STRC",
      "price": 99.965,
      "change": -0.04,
      "type": "stock"
    },
    {
      "symbol": "XLE",
      "name": "Energy ETF",
      "price": 60.88,
      "change": 3.24,
      "type": "stock"
    },
    {
      "symbol": "SMH",
      "name": "Semi ETF",
      "price": 378.075,
      "change": -3.54,
      "type": "stock"
    },
    {
      "symbol": "GLW",
      "name": "Corning Inc",
      "price": 137.625,
      "change": -3.34,
      "type": "stock"
    },
    {
      "symbol": "SPX",
      "name": "S&P 500",
      "price": 6475.25,
      "change": -1.52,
      "type": "index"
    },
    {
      "symbol": "NDX",
      "name": "NASDAQ 100",
      "price": 23513.6406,
      "change": -2.11,
      "type": "index"
    },
    {
      "symbol": "GOLD",
      "name": "Gold/oz",
      "price": 4627.0,
      "change": -3.27,
      "type": "commodity"
    },
    {
      "symbol": "SILVER",
      "name": "Silver/oz",
      "price": 70.53,
      "change": -7.03,
      "type": "commodity"
    },
    {
      "symbol": "BZ",
      "name": "Brent Crude",
      "price": 109.06,
      "change": 7.81,
      "type": "commodity"
    },
    {
      "symbol": "CL",
      "name": "WTI Crude",
      "price": 112.26,
      "change": 12.13,
      "type": "commodity"
    },
    {
      "symbol": "USDAUD",
      "name": "USD/AUD",
      "price": 1.4541,
      "change": 0.63,
      "type": "forex"
    }
  ],
  "lastUpdated": "2026-04-03T00:40:13.606646"
}